Workbook

Sheet Assumptions
A1: TNPM Platform — Cost Estimate (Build-From-Scratch)
A2: Currency: VND (blended Vietnam mid-tier rate, 2026)
A3: Methodology: Bottom-up MM x Role rate. 1 MM = 22 ngày x 8h = 176 effective hours.
A5: # | B5: Role | C5: Rate (VND/MM) | D5: Seniority | E5: Note
A6: 1 | B6: Tech Lead / Solution Architect | C6: 60000000 | D6: 10+ yrs | E6: Decision kiến trúc, code review, mentoring
A7: 2 | B7: Senior Backend Engineer | C7: 50000000 | D7: 7-10 yrs | E7: Java/Spring Boot 3.2 / Vert.x / Kafka / jOOQ
A8: 3 | B8: Mid Backend Engineer | C8: 35000000 | D8: 3-5 yrs | E8: Implement domain, test, code review junior
A9: 4 | B9: Senior Frontend Engineer | C9: 45000000 | D9: 5+ yrs | E9: React/TS, lead FE module, design system
A10: 5 | B10: Mid Frontend Engineer | C10: 30000000 | D10: 2-4 yrs | E10: Build page, integrate API, write test
A11: 6 | B11: DevOps / Platform Engineer | C11: 45000000 | D11: 5+ yrs | E11: K8s, Kafka/RabbitMQ, ES, Prometheus, CI/CD
A12: 7 | B12: Security Engineer | C12: 50000000 | D12: 5+ yrs | E12: Pentest, NHNN compliance, audit log design
A13: 8 | B13: QA Lead / Test Architect | C13: 35000000 | D13: 5+ yrs | E13: Test strategy, automation lead
A14: 9 | B14: QA Engineer | C14: 22000000 | D14: 2-4 yrs | E14: E2E, smoke, regression, manual UAT
A15: 10 | B15: Project Manager | C15: 40000000 | D15: 5+ yrs | E15: Schedule, stakeholder, risk, billing
A16: 11 | B16: Business Analyst | C16: 35000000 | D16: 3-5 yrs | E16: Refine spec, user story, UAT support
A17: 12 | B17: UX/UI Designer | C17: 35000000 | D17: 3-5 yrs | E17: Wireframe, design system, prototype
A19: Global parameters
A20: USD/VND exchange rate | B20: 24500
A21: Contingency % (Standard scenario) | B21: 0.15
A22: Project Overhead % | B22: 0.1
A23: Contingency % (Lean) | B23: 0.1
A24: Contingency % (Safe) | B24: 0.25
A25: Lean direct labor reduction % | B25: 0.1
A26: Safe indirect cost increase % | B26: 0.2

Sheet Effort_by_Module
A1: Effort by Module — Man-Month per Role
A3: Phase | B3: Module / Service | C3: BE Senior | D3: BE Mid | E3: FE Senior | F3: FE Mid | G3: QA Lead | H3: QA Eng | I3: Other (DevOps/Sec/TL) | J3: Total MM | K3: Module Cost (VND)
A4: Phase 1 | B4: iam-service (multi-tenant, RBAC, OAuth2/JWT) | C4: 1.5 | D4: 2.5 | E4: 0 | F4: 0 | G4: 0 | H4: 0 | I4: 0 | J4: =SUM(C4:I4) -> 4 | K4: =C4*Assumptions!$C$7+D4*Assumptions!$C$8+E4*Assumptions!$C$9+F4*Assumptions!$C$10+G4*Assumptions!$C$13+H4*Assumptions!$C$14+I4*44375000 -> 162500000
A5: Phase 1 | B5: portfolio-service (Portfolio>Project>Building>Floor>Space>Unit — 8 NEW) | C5: 1 | D5: 1 | E5: 0 | F5: 0 | G5: 0 | H5: 0 | I5: 0 | J5: =SUM(C5:I5) -> 2 | K5: =C5*Assumptions!$C$7+D5*Assumptions!$C$8+E5*Assumptions!$C$9+F5*Assumptions!$C$10+G5*Assumptions!$C$13+H5*Assumptions!$C$14+I5*44375000 -> 85000000
A6: Phase 1 | B6: customer-service (REUSE + extend property segment) | C6: 0.5 | D6: 1 | E6: 0 | F6: 0 | G6: 0 | H6: 0 | I6: 0 | J6: =SUM(C6:I6) -> 1.5 | K6: =C6*Assumptions!$C$7+D6*Assumptions!$C$8+E6*Assumptions!$C$9+F6*Assumptions!$C$10+G6*Assumptions!$C$13+H6*Assumptions!$C$14+I6*44375000 -> 60000000
A7: Phase 1 | B7: contract-service P1 (service contract base) | C7: 1 | D7: 1.5 | E7: 0 | F7: 0 | G7: 0 | H7: 0 | I7: 0 | J7: =SUM(C7:I7) -> 2.5 | K7: =C7*Assumptions!$C$7+D7*Assumptions!$C$8+E7*Assumptions!$C$9+F7*Assumptions!$C$10+G7*Assumptions!$C$13+H7*Assumptions!$C$14+I7*44375000 -> 102500000
A8: Phase 1 | B8: billing-service P1 (fee, rate, meter EVN bậc thang, invoice batch) | C8: 2 | D8: 3 | E8: 0 | F8: 0 | G8: 0 | H8: 0 | I8: 0 | J8: =SUM(C8:I8) -> 5 | K8: =C8*Assumptions!$C$7+D8*Assumptions!$C$8+E8*Assumptions!$C$9+F8*Assumptions!$C$10+G8*Assumptions!$C$13+H8*Assumptions!$C$14+I8*44375000 -> 205000000
A9: Phase 1 | B9: payment-service P1 (cash, debt ledger, MSB/Timi base) | C9: 1.5 | D9: 2 | E9: 0 | F9: 0 | G9: 0 | H9: 0 | I9: 0 | J9: =SUM(C9:I9) -> 3.5 | K9: =C9*Assumptions!$C$7+D9*Assumptions!$C$8+E9*Assumptions!$C$9+F9*Assumptions!$C$10+G9*Assumptions!$C$13+H9*Assumptions!$C$14+I9*44375000 -> 145000000
A10: Phase 1 | B10: operations-service P1 (Service Request, complaint ticket) | C10: 1 | D10: 1 | E10: 0 | F10: 0 | G10: 0 | H10: 0 | I10: 0 | J10: =SUM(C10:I10) -> 2 | K10: =C10*Assumptions!$C$7+D10*Assumptions!$C$8+E10*Assumptions!$C$9+F10*Assumptions!$C$10+G10*Assumptions!$C$13+H10*Assumptions!$C$14+I10*44375000 -> 85000000
A11: Phase 1 | B11: notification-service P1 (template SMS/Email) | C11: 0.5 | D11: 1 | E11: 0 | F11: 0 | G11: 0 | H11: 0 | I11: 0 | J11: =SUM(C11:I11) -> 1.5 | K11: =C11*Assumptions!$C$7+D11*Assumptions!$C$8+E11*Assumptions!$C$9+F11*Assumptions!$C$10+G11*Assumptions!$C$13+H11*Assumptions!$C$14+I11*44375000 -> 60000000
A12: Phase 1 | B12: FE P1 (~12 page core: portfolio, customer, contract, billing, debt, SR, setting) | C12: 0 | D12: 0 | E12: 2.5 | F12: 5.5 | G12: 0 | H12: 0 | I12: 0 | J12: =SUM(C12:I12) -> 8 | K12: =C12*Assumptions!$C$7+D12*Assumptions!$C$8+E12*Assumptions!$C$9+F12*Assumptions!$C$10+G12*Assumptions!$C$13+H12*Assumptions!$C$14+I12*44375000 -> 277500000
A13: Phase 1 | B13: QA P1 (smoke + integration + E2E) | C13: 0 | D13: 0 | E13: 0 | F13: 0 | G13: 1.5 | H13: 4.5 | I13: 0 | J13: =SUM(C13:I13) -> 6 | K13: =C13*Assumptions!$C$7+D13*Assumptions!$C$8+E13*Assumptions!$C$9+F13*Assumptions!$C$10+G13*Assumptions!$C$13+H13*Assumptions!$C$14+I13*44375000 -> 151500000
A14: Phase 2 | B14: payment-service full (gateway VNPay/MoMo, auto-debit, webhook security) | C14: 1.5 | D14: 1.5 | E14: 0 | F14: 0 | G14: 0 | H14: 0 | I14: 0 | J14: =SUM(C14:I14) -> 3 | K14: =C14*Assumptions!$C$7+D14*Assumptions!$C$8+E14*Assumptions!$C$9+F14*Assumptions!$C$10+G14*Assumptions!$C$13+H14*Assumptions!$C$14+I14*44375000 -> 127500000
A15: Phase 2 | B15: vendor-service (12 NEW: master, KPI, 3-way match, approval 4-step) | C15: 3.5 | D15: 4.5 | E15: 0 | F15: 0 | G15: 0 | H15: 0 | I15: 0 | J15: =SUM(C15:I15) -> 8 | K15: =C15*Assumptions!$C$7+D15*Assumptions!$C$8+E15*Assumptions!$C$9+F15*Assumptions!$C$10+G15*Assumptions!$C$13+H15*Assumptions!$C$14+I15*44375000 -> 332500000
... A38: Cross-cutting | B38: Knowledge transfer + onboarding + ramp-up buffer | C38: 0 | D38: 0 | E38: 0 | F38: 0 | G38: 0 | H38: 0 | I38: 10 | J38: =SUM(C38:I38) -> 10 | K38: =C38*Assumptions!$C$7+D38*Assumptions!$C$8+E38*Assumptions!$C$9+F38*Assumptions!$C$10+G38*Assumptions!$C$13+H38*Assumptions!$C$14+I38*44375000 -> 443750000
A39: TỔNG | B39: Direct Labor (toàn bộ effort) | C39: =SUM(C4:C38) -> 26 | D39: =SUM(D4:D38) -> 35 | E39: =SUM(E4:E38) -> 7.5 | F39: =SUM(F4:F38) -> 16.5 | G39: =SUM(G4:G38) -> 4 | H39: =SUM(H4:H38) -> 12 | I39: =SUM(I4:I38) -> 42 | J39: =SUM(J4:J38) -> 143 | K39: =SUM(K4:K38) -> 5625250000
A41: Subtotal theo Phase
A42: Phase 1 | J42: =SUMIF(A4:A38,"Phase 1",J4:J38) -> 36 | K42: =SUMIF(A4:A38,"Phase 1",K4:K38) -> 1334000000
A43: Phase 2 | J43: =SUMIF(A4:A38,"Phase 2",J4:J38) -> 25 | K43: =SUMIF(A4:A38,"Phase 2",K4:K38) -> 926000000
A44: Phase 3 | J44: =SUMIF(A4:A38,"Phase 3",J4:J38) -> 28.5 | K44: =SUMIF(A4:A38,"Phase 3",K4:K38) -> 1086000000
A45: Portal+Integration | J45: =SUMIF(A4:A38,"Portal+Integration",J4:J38) -> 11.5 | K45: =SUMIF(A4:A38,"Portal+Integration",K4:K38) -> 415500000
A46: Cross-cutting | J46: =SUMIF(A4:A38,"Cross-cutting",J4:J38) -> 42 | K46: =SUMIF(A4:A38,"Cross-cutting",K4:K38) -> 1863750000

Sheet Indirect_Costs
A1: Indirect Costs — Infra, Tools, 3rd-party
A3: # | B3: Hạng mục | C3: Giá trị (VND) | D3: Ghi chú
A4: 1 | B4: Cloud infra (dev + staging + prod) 18 tháng | C4: 600000000 | D4: K8s managed cluster, DB (PostgreSQL HA), Redis, ES cluster 3-node, RabbitMQ, S3, monitoring stack
A5: 2 | B5: Tools & License | C5: 100000000 | D5: Jira/Confluence team, Figma Pro, GitLab Premium, Snyk + SonarQube
A6: 3 | B6: 3rd-party — Pentest 1 round | C6: 80000000 | D6: External pentest firm, full report + retest
A7: 4 | B7: 3rd-party — MSB Pay onboarding & cert | C7: 50000000 | D7: Merchant onboarding fee + UAT cost
A8: 5 | B8: 3rd-party — Timi API access | C8: 30000000 | D8: Setup + integration fee
A9: 6 | B9: 3rd-party — sInvoice license | C9: 40000000 | D9: Hoá đơn điện tử license + integration
A10: TỔNG | B10: Indirect Cost Subtotal | C10: =SUM(C4:C9) -> 900000000

Sheet Summary
A1: TNPM Platform — Cost Summary (Build-From-Scratch)
A2: Scope: Web Admin + 12 microservice BE (Phase 1-3) + Owner/Vendor Portal + Integration MSB/Timi/VNPay/MoMo
A4: Hạng mục | B4: Lean (~6.6tỷ) | C4: Standard (~8.1tỷ) | D4: Safe (~9.0tỷ) | E4: Ghi chú
A5: Direct Labor | B5: =Effort_by_Module!K39*(1-Assumptions!$B$25) -> 5062725000 | C5: =Effort_by_Module!K39 -> 5625250000 | D5: =Effort_by_Module!K39 -> 5625250000 | E5: Sum effort × rate per role
A6: Indirect Cost | B6: =Indirect_Costs!C10 -> 900000000 | C6: =Indirect_Costs!C10 -> 900000000 | D6: =Indirect_Costs!C10*(1+Assumptions!$B$26) -> 1080000000 | E6: Infra + Tools + 3rd-party
A7: Subtotal (DL + IC) | B7: =B5+B6 -> 5962725000 | C7: =C5+C6 -> 6525250000 | D7: =D5+D6 -> 6705250000
A8: Contingency | B8: =B7*Assumptions!$B$23 -> 596272500 | C8: =C7*Assumptions!$B$21 -> 978787500 | D8: =D7*Assumptions!$B$24 -> 1676312500 | E8: Buffer rủi ro
A9: Project Overhead | B9: =B7*Assumptions!$B$22 -> 596272500 | C9: =C7*Assumptions!$B$22 -> 652525000 | D9: =D7*Assumptions!$B$22 -> 670525000 | E9: PM admin, license amortization
A10: TỔNG VND | B10: =B7+B8+B9 -> 7155270000 | C10: =C7+C8+C9 -> 8156562500 | D10: =D7+D8+D9 -> 9052087500
A11: TỔNG USD (tham chiếu) | B11: =B10/Assumptions!$B$20 -> 292051.84 | C11: =C10/Assumptions!$B$20 -> 332920.92 | D11: =D10/Assumptions!$B$20 -> 369472.96 | E11: @ 1 USD = 24,500 VND
A14: Effort Summary
A15: Bucket | B15: MM
A16: Phase 1 (BE + FE + QA) | B16: =SUMIF(Effort_by_Module!A4:A38,"Phase 1",Effort_by_Module!J4:J38) -> 36
A17: Phase 2 (BE + FE + QA) | B17: =SUMIF(Effort_by_Module!A4:A38,"Phase 2",Effort_by_Module!J4:J38) -> 25
A18: Phase 3 (BE + FE + QA) | B18: =SUMIF(Effort_by_Module!A4:A38,"Phase 3",Effort_by_Module!J4:J38) -> 28.5
A19: Portal + Integration | B19: =SUMIF(Effort_by_Module!A4:A38,"Portal+Integration",Effort_by_Module!J4:J38) -> 11.5
A20: Cross-cutting (TL/PM/BA/UX/DevOps/Sec) | B20: =SUMIF(Effort_by_Module!A4:A38,"Cross-cutting",Effort_by_Module!J4:J38) -> 42
A21: TỔNG MM | B21: =B16+B17+B18+B19+B20 -> 143
A24: Khuyến nghị
A25: 1. Dùng Standard ~8.1 tỷ VND làm cost basis chào TNTech để align internal.
A26: 2. Lean ~6.6 tỷ chỉ khả thi khi Reborn reuse retail >= 60% + team senior đa năng.
A27: 3. Safe ~9.0 tỷ khi có CĐT lớn cần SSO/SAML, data migration, NHNN compliance scope full.
A28: 4. Out-of-scope (tính riêng): Mobile cư dân +1.5tỷ, AI debt +800M, POS integration, Data migration, Hotline call center, On-premise deploy.
A29: 5. Cost này KHÔNG phải pricing cho TNPM — pricing = cost × (1 + margin 30-50%) tuỳ engagement model (xem 07-business-case/).
A30: 6. Annual maintenance fee (sau go-live) = 15-20% cost build/năm, tính riêng.

Sheet Scenario_Comparison
A1: Scenario Comparison & Sensitivity
A2: Để TNTech chỉnh tham số trực tiếp và xem tác động lên TỔNG.
A4: Scenario | B4: Direct Labor (VND) | C4: Indirect (VND) | D4: Contingency % | E4: Overhead % | F4: TỔNG VND
A5: Lean | B5: =Effort_by_Module!K39*(1-Assumptions!$B$25) -> 5062725000 | C5: =Indirect_Costs!C10 -> 900000000 | D5: =Assumptions!$B$23 -> 0.1 | E5: =Assumptions!$B$22 -> 0.1 | F5: =(B5+C5)*(1+D5+E5) -> 7.15527e+09
A6: Standard | B6: =Effort_by_Module!K39 -> 5625250000 | C6: =Indirect_Costs!C10 -> 900000000 | D6: =Assumptions!$B$21 -> 0.15 | E6: =Assumptions!$B$22 -> 0.1 | F6: =(B6+C6)*(1+D6+E6) -> 8156562500
A7: Safe | B7: =Effort_by_Module!K39 -> 5625250000 | C7: =Indirect_Costs!C10*(1+Assumptions!$B$26) -> 1080000000 | D7: =Assumptions!$B$24 -> 0.25 | E7: =Assumptions!$B$22 -> 0.1 | F7: =(B7+C7)*(1+D7+E7) -> 9052087500
A10: Out-of-scope add-ons (tính riêng nếu TNPM yêu cầu)
A11: Add-on | B11: Ước tính VND | C11: MM | D11: Khi nào cần
A12: Mobile cư dân Timi-like (React Native) | B12: 1500000000 | C12: 22 | D12: Khi TNPM không dùng app Timi sẵn có
A13: AI phân tích công nợ | B13: 800000000 | C13: 12 | D13: Phase 4 — cần data >= 6 tháng
A14: POS Integration cho TTTM tenant | B14: 400000000 | C14: 6 | D14: Khi tenant TTTM lớn yêu cầu turnover auto
A15: Data migration từ hệ thống cũ TNPM | B15: 600000000 | C15: 9 | D15: Tuỳ độ phức tạp data source
A16: Hotline call center integration | B16: 300000000 | C16: 4 | D16: Cần đối tác viễn thông + thiết bị
A17: On-premise deployment package | B17: 500000000 | C17: 7 | D17: Khi TNPM yêu cầu on-prem thay vì cloud
A18: SSO/SAML cho CĐT lớn (per CĐT) | B18: 250000000 | C18: 3.5 | D18: Vinhomes, AEON, etc.

Sheet OPEX_Segments
A1: OPEX — 4 segment scale TNPM (chưa khoá quy mô)
A2: Chọn segment phù hợp khi TNPM xác nhận quy mô. TNPM ROX Key hiện tại likely là L.
A4: Dimension | B4: S — Pilot | C4: M — Mid-scale | D4: L — Large (TNPM likely) | E4: XL — Enterprise | F4: Note
A5: # Projects (dự án) | B5: 1-3 | C5: 4-15 | D5: 15-50 | E5: 50+ | F5: Multi-tenant project
A6: # Units / Space | B6: ≤ 500 | C6: 500-3,000 | D6: 3,000-15,000 | E6: 15,000+ | F6: Đơn vị nhà/mặt bằng
A7: # Customers (cư dân + B2B) | B7: ≤ 2,000 | C7: 2k-15k | D7: 15k-60k | E7: 60k+ | F7: Active customers
A8: Invoices / tháng | B8: ~1,000 | C8: 3k-15k | D8: 20k-60k | E8: 80k+ | F8: Hoá đơn phát hành định kỳ
A9: Payment tx / tháng | B9: ~700 | C9: 2k-10k | D9: 15k-45k | E9: 60k+ | F9: Giao dịch thanh toán
A10: Concurrent users (peak) | B10: ~50 | C10: 100-300 | D10: 400-1,000 | E10: 1,500+ | F10: Cao điểm ngày mồng 1-8
A11: Mô tả thực tế | B11: Pilot 1-2 chung cư | C11: TNPM năm đầu — VP + KCN nhỏ + chung cư | D11: Toàn portfolio ROX Key — 7 loại property | E11: Mở white-label cho 3rd-party CĐT (Vinhomes, Sun Group...)
A14: Volume estimates / tháng (input cho Pass-through sheet)
A15: Volume metric | B15: S | C15: M | D15: L | E15: XL | F15: Đơn giá tham chiếu
A16: Invoices / tháng | B16: 1000 | C16: 9000 | D16: 40000 | E16: 100000 | F16: — (đầu vào cho SMS/Email/Zalo/sInvoice)
A17: Payment transactions / tháng | B17: 700 | C17: 6000 | D17: 35000 | E17: 80000 | F17: MSB ~5,000-10,000đ/tx, VNPay/MoMo ~3,000đ/tx
A18: SMS / tháng (5x invoice) | B18: 5000 | C18: 45000 | D18: 200000 | E18: 500000 | F18: Viettel/VNPT ~600đ/SMS, volume contract ~400đ
A19: Email / tháng (5x invoice) | B19: 5000 | C19: 45000 | D19: 200000 | E19: 500000 | F19: SendGrid/Mailgun ~100đ/email
A20: Zalo OA / tháng (1x invoice) | B20: 1000 | C20: 9000 | D20: 40000 | E20: 100000 | F20: ~500đ/notification
A21: sInvoice (HĐ điện tử) / tháng | B21: 1000 | C21: 9000 | D21: 40000 | E21: 100000 | F21: ~1,000-2,000đ/HĐ tuỳ provider

Sheet OPEX_PlatOps
A1: Platform Operating Cost (PlatOps) per segment — VND/tháng
A2: 9 component / segment. Đơn vị: triệu VND/tháng. Reborn/operator gánh — không phụ thuộc volume tx.
A4: # | B4: Component | C4: S | D4: M | E4: L | F4: XL
A5: 1 | B5: Cloud Infrastructure (K8s, DB HA, Redis, ES, RabbitMQ, S3) | C5: 25000000 | D5: 80000000 | E5: 250000000 | F5: 700000000
A6: 2 | B6: Licenses & Tools (monitoring, security scan, Jira/Figma) | C6: 8000000 | D6: 15000000 | E6: 30000000 | F6: 60000000
A7: 3 | B7: DevOps / SRE team (FTE × loaded rate) | C7: 22500000 | D7: 45000000 | E7: 100000000 | F7: 220000000
A8: 4 | B8: Application Support L1/L2/L3 | C8: 15000000 | D8: 35000000 | E8: 90000000 | F8: 220000000
A9: 5 | B9: Annual Maintenance & Evolution (15-20% cost build/12) | C9: 100000000 | D9: 110000000 | E9: 130000000 | F9: 160000000
A10: 6 | B10: Backup & DR (cross-AZ, 30d retention, RTO 4h) | C10: 5000000 | D10: 15000000 | E10: 45000000 | F10: 120000000
A11: 7 | B11: Compliance & Security Audit (pentest + NHNN audit /12) | C11: 10000000 | D11: 15000000 | E11: 25000000 | F11: 40000000
A12: 8 | B12: Training & Documentation | C12: 3000000 | D12: 8000000 | E12: 15000000 | F12: 30000000
A13: 9 | B13: Vendor management buffer (cloud overages, ES upgrade) | C13: 10000000 | D13: 20000000 | E13: 50000000 | F13: 100000000
B14: TỔNG PlatOps / tháng | C14: =SUM(C5:C13) -> 198500000 | D14: =SUM(D5:D13) -> 343000000 | E14: =SUM(E5:E13) -> 735000000 | F14: =SUM(F5:F13) -> 1650000000
B15: TỔNG PlatOps / năm | C15: =C14*12 -> 2382000000 | D15: =D14*12 -> 4116000000 | E15: =E14*12 -> 8820000000 | F15: =F14*12 -> 19800000000
B17: Ratio PlatOps/năm vs CAPEX (Standard 8.16 tỷ) | C17: =C15/Summary!C10 -> 0.29203479 | D17: =D15/Summary!C10 -> 0.50462434 | E17: =E15/Summary!C10 -> 1.0813379 | F17: =F15/Summary!C10 -> 2.4274932

Sheet OPEX_PassThrough
A1: Pass-through Usage Cost per segment — VND/tháng
A2: Volume × đơn giá. TNPM trực tiếp gánh — không phụ thuộc engagement model. Khuyến nghị TNPM thu lại từ KH cuối.
A4: # | B4: Component | C4: S | D4: M | E4: L | F4: XL
A5: 1 | B5: MSB / VNPay transaction fee (blended 5,000đ/tx) | C5: =OPEX_Segments!B17*5000 -> 3500000 | D5: =OPEX_Segments!C17*5000 -> 30000000 | E5: =OPEX_Segments!D17*5000 -> 175000000 | F5: =OPEX_Segments!E17*5000 -> 400000000
A6: 2 | B6: SMS OTP + nhắc nợ (600đ/SMS) | C6: =OPEX_Segments!B18*600 -> 3000000 | D6: =OPEX_Segments!C18*600 -> 27000000 | E6: =OPEX_Segments!D18*600 -> 120000000 | F6: =OPEX_Segments!E18*600 -> 300000000
A7: 3 | B7: Email (100đ/email) | C7: =OPEX_Segments!B19*100 -> 500000 | D7: =OPEX_Segments!C19*100 -> 4500000 | E7: =OPEX_Segments!D19*100 -> 20000000 | F7: =OPEX_Segments!E19*100 -> 50000000
A8: 4 | B8: Zalo OA (500đ/noti) | C8: =OPEX_Segments!B20*500 -> 500000 | D8: =OPEX_Segments!C20*500 -> 4500000 | E8: =OPEX_Segments!D20*500 -> 20000000 | F8: =OPEX_Segments!E20*500 -> 50000000
A9: 5 | B9: sInvoice (1,000đ/HĐ) | C9: =OPEX_Segments!B21*1000 -> 1000000 | D9: =OPEX_Segments!C21*1000 -> 9000000 | E9: =OPEX_Segments!D21*1000 -> 40000000 | F9: =OPEX_Segments!E21*1000 -> 100000000
B10: TỔNG Pass-through / tháng | C10: =SUM(C5:C9) -> 8500000 | D10: =SUM(D5:D9) -> 75000000 | E10: =SUM(E5:E9) -> 375000000 | F10: =SUM(F5:F9) -> 900000000
B11: TỔNG Pass-through / năm | C11: =C10*12 -> 102000000 | D11: =D10*12 -> 900000000 | E11: =E10*12 -> 4500000000 | F11: =F10*12 -> 10800000000

Sheet OPEX_Summary
A1: OPEX Summary — Annual + TCO 3 năm
A2: Tổng hợp PlatOps + Pass-through và Total Cost of Ownership 3 năm cho từng segment.
A4: Hạng mục | B4: S — Pilot | C4: M — Mid | D4: L — Large | E4: XL — Enterprise | F4: Note
A5: PlatOps / năm | B5: =OPEX_PlatOps!C15 -> 2382000000 | C5: =OPEX_PlatOps!D15 -> 4116000000 | D5: =OPEX_PlatOps!E15 -> 8820000000 | E5: =OPEX_PlatOps!F15 -> 19800000000 | F5: Reborn/operator gánh
A6: Pass-through / năm | B6: =OPEX_PassThrough!C11 -> 102000000 | C6: =OPEX_PassThrough!D11 -> 900000000 | D6: =OPEX_PassThrough!E11 -> 4500000000 | E6: =OPEX_PassThrough!F11 -> 10800000000 | F6: TNPM gánh, scale volume
A7: TỔNG OPEX / năm | B7: =B5+B6 -> 2484000000 | C7: =C5+C6 -> 5016000000 | D7: =D5+D6 -> 13320000000 | E7: =E5+E6 -> 30600000000
A9: TCO 3 năm — TNPM (Reborn managed SaaS, margin PlatOps 35%)
A10: Hạng mục | B10: S | C10: M | D10: L | E10: XL | F10: Note
A11: Year 1 — CAPEX chào TNPM (Standard + 35% margin) | B11: =Summary!C10*1.35 -> 11011359375 | C11: =Summary!C10*1.35 -> 11011359375 | D11: =Summary!C10*1.35 -> 11011359375 | E11: =Summary!C10*1.35 -> 11011359375 | F11: 1 lần, có Lean/Safe option
A12: Year 1-2-3 — PlatOps × 1.35 margin / năm | B12: =B5*1.35 -> 3215700000 | C12: =C5*1.35 -> 5556600000 | D12: =D5*1.35 -> 11907000000 | E12: =E5*1.35 -> 26730000000 | F12: SaaS subscription bill TNPM
A13: Year 1-2-3 — Pass-through at-cost / năm | B13: =B6 -> 102000000 | C13: =C6 -> 900000000 | D13: =D6 -> 4500000000 | E13: =E6 -> 10800000000 | F13: Bill at-cost, transparent
A14: Year 1 total TNPM trả | B14: =B11+B12+B13 -> 14329059375 | C14: =C11+C12+C13 -> 17467959375 | D14: =D11+D12+D13 -> 27418359375 | E14: =E11+E12+E13 -> 48541359375 | F14: CAPEX + 1 năm OPEX
A15: Year 2 total | B15: =B12+B13 -> 3317700000 | C15: =C12+C13 -> 6456600000 | D15: =D12+D13 -> 16407000000 | E15: =E12+E13 -> 37530000000 | F15: Subscription only
A16: Year 3 total | B16: =B12+B13 -> 3317700000 | C16: =C12+C13 -> 6456600000 | D16: =D12+D13 -> 16407000000 | E16: =E12+E13 -> 37530000000 | F16: Subscription only
A17: TCO 3 năm | B17: =B14+B15+B16 -> 20964459375 | C17: =C14+C15+C16 -> 30381159375 | D17: =D14+D15+D16 -> 60232359375 | E17: =E14+E15+E16 -> 123601359375 | F17: Số TNPM cần budget
A20: Khuyến nghị OPEX
A21: 1. TNPM ROX Key hiện tại likely thuộc segment L — confirm với TNPM trong buổi discovery để chốt.
A22: 2. Pass-through cost (MSB tx, SMS, sInvoice) khuyến nghị TNPM thu lại từ KH cuối — không gánh trên P&L vận hành.
A23: 3. PlatOps L = 8.82 tỷ/năm ≈ 108% CAPEX (8.16 tỷ) — chuẩn industry SaaS B2B năm 1-2, sẽ giảm xuống ~60% năm 3+ qua optimization.
A24: 4. SaaS managed model: Reborn margin PlatOps 25-40% (chốt 35% trong sheet này). Pass-through bill at-cost transparent.
A25: 5. Hybrid: Reborn host 12-18 tháng đầu, TNPM có option migrate on-premise sau — minimize risk 2 bên.
A26: 6. Industry benchmark TCO 3 năm: Yardi 50-80 tỷ, MRI 60-100 tỷ. Local custom + Reborn managed nên rơi 50-65 tỷ (L segment) → competitive.
